controlnet_hinter.py
annotator/__init__.py
annotator/util.py
annotator/canny/__init__.py
annotator/hed/__init__.py
annotator/midas/__init__.py
annotator/midas/api.py
annotator/midas/utils.py
annotator/midas/midas/__init__.py
annotator/midas/midas/base_model.py
annotator/midas/midas/blocks.py
annotator/midas/midas/dpt_depth.py
annotator/midas/midas/midas_net.py
annotator/midas/midas/midas_net_custom.py
annotator/midas/midas/transforms.py
annotator/midas/midas/vit.py
annotator/mlsd/__init__.py
annotator/mlsd/utils.py
annotator/mlsd/models/__init__.py
annotator/mlsd/models/mbv2_mlsd_large.py
annotator/mlsd/models/mbv2_mlsd_tiny.py
annotator/openpose/__init__.py
annotator/openpose/body.py
annotator/openpose/hand.py
annotator/openpose/model.py
annotator/openpose/util.py
annotator/uniformer/__init__.py
annotator/uniformer/configs/__init__.py
annotator/uniformer/configs/_base_/__init__.py
annotator/uniformer/configs/_base_/default_runtime.py
annotator/uniformer/configs/_base_/datasets/__init__.py
annotator/uniformer/configs/_base_/datasets/ade20k.py
annotator/uniformer/configs/_base_/datasets/chase_db1.py
annotator/uniformer/configs/_base_/datasets/cityscapes.py
annotator/uniformer/configs/_base_/datasets/cityscapes_769x769.py
annotator/uniformer/configs/_base_/datasets/drive.py
annotator/uniformer/configs/_base_/datasets/hrf.py
annotator/uniformer/configs/_base_/datasets/pascal_context.py
annotator/uniformer/configs/_base_/datasets/pascal_context_59.py
annotator/uniformer/configs/_base_/datasets/pascal_voc12.py
annotator/uniformer/configs/_base_/datasets/pascal_voc12_aug.py
annotator/uniformer/configs/_base_/datasets/stare.py
annotator/uniformer/configs/_base_/models/__init__.py
annotator/uniformer/configs/_base_/models/ann_r50-d8.py
annotator/uniformer/configs/_base_/models/apcnet_r50-d8.py
annotator/uniformer/configs/_base_/models/ccnet_r50-d8.py
annotator/uniformer/configs/_base_/models/cgnet.py
annotator/uniformer/configs/_base_/models/danet_r50-d8.py
controlnet_hinter-0.0.5.dist-info/LICENSE
controlnet_hinter-0.0.5.dist-info/METADATA
controlnet_hinter-0.0.5.dist-info/WHEEL
controlnet_hinter-0.0.5.dist-info/top_level.txt
controlnet_hinter-0.0.5.dist-info/RECORD
